HeWoYibubuBushuKubernetesJiqun/README.md
HeWoYibubuBushuKubernetesJiqun/__init__.py
HeWoYibubuBushuKubernetesJiqun/__main__.py
HeWoYibubuBushuKubernetesJiqun/file.epub
HeWoYibubuBushuKubernetesJiqun/index.html
HeWoYibubuBushuKubernetesJiqun/css/__init__.py
HeWoYibubuBushuKubernetesJiqun/css/annotations.css
HeWoYibubuBushuKubernetesJiqun/css/main.css
HeWoYibubuBushuKubernetesJiqun/css/normalize.css
HeWoYibubuBushuKubernetesJiqun/css/popup.css
HeWoYibubuBushuKubernetesJiqun/font/__init__.py
HeWoYibubuBushuKubernetesJiqun/font/fontello.eot
HeWoYibubuBushuKubernetesJiqun/font/fontello.svg
HeWoYibubuBushuKubernetesJiqun/font/fontello.ttf
HeWoYibubuBushuKubernetesJiqun/font/fontello.woff
HeWoYibubuBushuKubernetesJiqun/img/__init__.py
HeWoYibubuBushuKubernetesJiqun/img/annotator-glyph-sprite.png
HeWoYibubuBushuKubernetesJiqun/img/annotator-icon-sprite.png
HeWoYibubuBushuKubernetesJiqun/img/apple-touch-icon.png
HeWoYibubuBushuKubernetesJiqun/img/cancelfullscreen.png
HeWoYibubuBushuKubernetesJiqun/img/close.png
HeWoYibubuBushuKubernetesJiqun/img/fullscreen.png
HeWoYibubuBushuKubernetesJiqun/img/loader.gif
HeWoYibubuBushuKubernetesJiqun/img/menu-icon.png
HeWoYibubuBushuKubernetesJiqun/img/save.png
HeWoYibubuBushuKubernetesJiqun/img/saved.png
HeWoYibubuBushuKubernetesJiqun/img/settings-s.png
HeWoYibubuBushuKubernetesJiqun/img/settings.png
HeWoYibubuBushuKubernetesJiqun/img/star.png
HeWoYibubuBushuKubernetesJiqun/js/__init__.py
HeWoYibubuBushuKubernetesJiqun/js/epub.js
HeWoYibubuBushuKubernetesJiqun/js/epub.min.js
HeWoYibubuBushuKubernetesJiqun/js/epub.min.map
HeWoYibubuBushuKubernetesJiqun/js/hooks.min.js
HeWoYibubuBushuKubernetesJiqun/js/hooks.min.map
HeWoYibubuBushuKubernetesJiqun/js/reader.js
HeWoYibubuBushuKubernetesJiqun/js/reader.js.map
HeWoYibubuBushuKubernetesJiqun/js/reader.min.js
HeWoYibubuBushuKubernetesJiqun/js/reader.min.map
HeWoYibubuBushuKubernetesJiqun/js/hooks/__init__.py
HeWoYibubuBushuKubernetesJiqun/js/hooks/extensions/__init__.py
he_wo_yibubu_bushu_kubernetes_jiqun-2024.3.4.0.dist-info/METADATA
he_wo_yibubu_bushu_kubernetes_jiqun-2024.3.4.0.dist-info/WHEEL
he_wo_yibubu_bushu_kubernetes_jiqun-2024.3.4.0.dist-info/entry_points.txt
he_wo_yibubu_bushu_kubernetes_jiqun-2024.3.4.0.dist-info/top_level.txt
he_wo_yibubu_bushu_kubernetes_jiqun-2024.3.4.0.dist-info/RECORD
